pympc/__init__.py
pympc/pympc.py
pympc/utils.py
pympc-1.4.0.dist-info/licenses/LICENSE.txt
test/__init__.py
test/benchmark.py
test/test_pympc.py
pympc-1.4.0.dist-info/METADATA
pympc-1.4.0.dist-info/WHEEL
pympc-1.4.0.dist-info/entry_points.txt
pympc-1.4.0.dist-info/top_level.txt
pympc-1.4.0.dist-info/RECORD
