Metadata-Version: 2.4
Name: pympc
Version: 1.4.0
Summary: minor planet checking
Home-page: https://github.com/lyalpha/pympc
Author: Joe Lyman
License: GNU General Public License v3 (GPLv3)
Classifier: Programming Language :: Python :: 3
Requires-Python: >=3.8
License-File: LICENSE.txt
Requires-Dist: ephem>=4.1
Requires-Dist: astropy>=4.2
Requires-Dist: numpy>=1.18
Requires-Dist: pandas>=1.0
Requires-Dist: pyerfa>=2.0.0.0
Requires-Dist: requests
Requires-Dist: rich>=14.0.0
Requires-Dist: loguru>=0.7.0
Dynamic: author
Dynamic: classifier
Dynamic: description
Dynamic: description-content-type
Dynamic: home-page
Dynamic: license
Dynamic: license-file
Dynamic: requires-dist
Dynamic: requires-python
Dynamic: summary
